ez_icons/__init__.py
ez_icons/black/3d_rotation.png
ez_icons/black/__init__.py
ez_icons/black/ac_unit.png
ez_icons/black/access_alarm.png
ez_icons/black/access_alarms.png
ez_icons/black/access_time.png
ez_icons/black/accessibility.png
ez_icons/black/accessible.png
ez_icons/black/account_balance.png
ez_icons/black/account_balance_wallet.png
ez_icons/black/account_box.png
ez_icons/black/account_circle.png
ez_icons/black/adb.png
ez_icons/black/add.png
ez_icons/black/add_a_photo.png
ez_icons/black/add_alarm.png
ez_icons/black/add_alert.png
ez_icons/black/add_box.png
ez_icons/black/add_circle.png
ez_icons/black/add_circle_outline.png
ez_icons/black/add_location.png
ez_icons/black/add_shopping_cart.png
ez_icons/black/add_to_photos.png
ez_icons/black/add_to_queue.png
ez_icons/black/adjust.png
ez_icons/black/airline_seat_flat.png
ez_icons/black/airline_seat_flat_angled.png
ez_icons/black/airline_seat_individual_suite.png
ez_icons/black/airline_seat_legroom_extra.png
ez_icons/black/airline_seat_legroom_normal.png
ez_icons/black/airline_seat_legroom_reduced.png
ez_icons/black/airline_seat_recline_extra.png
ez_icons/black/airline_seat_recline_normal.png
ez_icons/black/airplanemode_active.png
ez_icons/black/airplanemode_inactive.png
ez_icons/black/airplay.png
ez_icons/black/airport_shuttle.png
ez_icons/black/alarm.png
ez_icons/black/alarm_add.png
ez_icons/black/alarm_off.png
ez_icons/black/alarm_on.png
ez_icons/black/album.png
ez_icons/black/all_inclusive.png
ez_icons/black/all_out.png
ez_icons/black/android.png
ez_icons/black/announcement.png
ez_icons/black/apps.png
ez_icons/black/archive.png
ez_icons/black/arrow_back.png
ez_icons/black/arrow_downward.png
ez_icons/black/arrow_drop_down.png
ez_icons/black/arrow_drop_down_circle.png
ez_icons/black/arrow_drop_up.png
ez_icons/black/arrow_forward.png
ez_icons/black/arrow_upward.png
ez_icons/black/art_track.png
ez_icons/black/aspect_ratio.png
ez_icons/black/assessment.png
ez_icons/black/assignment.png
ez_icons-1.0.2.dist-info/LICENSE
ez_icons-1.0.2.dist-info/METADATA
ez_icons-1.0.2.dist-info/WHEEL
ez_icons-1.0.2.dist-info/top_level.txt
ez_icons-1.0.2.dist-info/RECORD
