Metadata-Version: 2.1
Name: ez-icons
Version: 1.0.2
Summary: Easily code complete your way to the Material Icons
Home-page: https://github.com/nielsvaes/ez_icons
Author: Niels Vaes
Author-email: nielsvaes@gmail.com
License: Apache 2.0
Platform: UNKNOWN
